cccs/__init__.py
cccs/common/__init__.py
cccs/common/chunk.py
cccs/common/classification.py
cccs/common/classification.yml
cccs/common/dict_utils.py
cccs/common/exceptions.py
cccs/common/hexdump.py
cccs/common/iprange.py
cccs/common/isotime.py
cccs/common/loader.py
cccs/common/log.py
cccs/common/logformat.py
cccs/common/memory_zip.py
cccs/common/net.py
cccs/common/net_static.py
cccs/common/path.py
cccs/common/random_user.py
cccs/common/security.py
cccs/common/str_utils.py
cccs/common/uid.py
cccs/datastore/__init__.py
cccs/datastore/bulk.py
cccs/datastore/collection.py
cccs/datastore/exceptions.py
cccs/datastore/store.py
cccs/datastore/support/__init__.py
cccs/datastore/support/build.py
cccs/datastore/support/schemas.py
cccs/filestore/__init__.py
cccs/filestore/transport/__init__.py
cccs/filestore/transport/azure.py
cccs/filestore/transport/base.py
cccs/filestore/transport/ftp.py
cccs/filestore/transport/http.py
cccs/filestore/transport/local.py
cccs/filestore/transport/s3.py
cccs/filestore/transport/sftp.py
cccs/odm/__init__.py
cccs/odm/base.py
cccs/odm/models/__init__.py
cccs/odm/models/config.py
cccs/remote/__init__.py
cccs/remote/datatypes/__init__.py
cccs/remote/datatypes/counters.py
cccs/remote/datatypes/events.py
cccs/remote/datatypes/hash.py
cccs/remote/datatypes/lock.py
cccs/remote/datatypes/set.py
cccs/remote/datatypes/user_quota_tracker.py
cccs/remote/datatypes/queues/__init__.py
cccs/remote/datatypes/queues/comms.py
cccs/remote/datatypes/queues/multi.py
cccs/remote/datatypes/queues/named.py
cccs/remote/datatypes/queues/priority.py
cccs-0.0.6.dist-info/LICENSE
cccs-0.0.6.dist-info/METADATA
cccs-0.0.6.dist-info/WHEEL
cccs-0.0.6.dist-info/top_level.txt
cccs-0.0.6.dist-info/RECORD
